README.md
setup.py
gfcc/__init__.py
gfcc/__main__.py
gfcc/gfcc.py
gfcc/utils.py
gfcc.egg-info/PKG-INFO
gfcc.egg-info/SOURCES.txt
gfcc.egg-info/dependency_links.txt
gfcc.egg-info/entry_points.txt
gfcc.egg-info/top_level.txt