Metadata-Version: 1.1
Name: gfcc
Version: 0.5
Summary: A layer of automation for ClearCase with a touch of git flavour
Home-page: https://github.com/bmpenuelas/gfcc
Author: Borja Penuelas
Author-email: bmpenuelas@gmail.com
License: MIT
Keywords: git clearcase cleartool
Platform: UNKNOWN
Classifier: Development Status :: 3 - Alpha
Classifier: Programming Language :: Python :: 3
